setup.py
debilinio_hrr/__init__.py
debilinio_hrr/one.py
debilinio_hrr/two.py
debilinio_hrr.egg-info/PKG-INFO
debilinio_hrr.egg-info/SOURCES.txt
debilinio_hrr.egg-info/dependency_links.txt
debilinio_hrr.egg-info/top_level.txt